[{"id":"262d58f6-d992-4969-9880-14df5a9dfa55","name":"Ivette Lezama","email":"ilezamac@hotmail.com","phone":"7182001633","active":true,"created_at":"2026-02-16T20:12:26.539847","pin":"575308","working_days":["Sun"],"working_start":"09:00:00","working_end":"17:00:00","photo_url":"https://ioppmvchszymwswtwsze.supabase.co/storage/v1/object/public/cleaner-photo/cleaner-photos/1771272530117-ykuget.jpeg","schedule":{"Sun": {"end": "5:00 PM", "start": "9:00 AM"}},"hourly_rate":30,"address":"6710 60th St, Ridgewood, NY 11385, 1 FL","priority":4,"unavailable_dates":[],"sms_consent":true,"notification_preferences":{"broadcast": {"sms": true, "push": true, "email": true}, "quiet_end": "\"07:00\"", "quiet_start": "\"22:00\"", "job_reminder": {"sms": true, "push": true, "email": true}, "daily_summary": {"sms": true, "push": true, "email": true}, "job_cancelled": {"sms": true, "push": true, "email": true}, "job_assignment": {"sms": true, "push": true, "email": true}, "job_rescheduled": {"sms": true, "push": true, "email": true}}}, 
 {"id":"85c9264f-1f07-459c-9972-0523db69d5a3","name":"Jeff Tucker","email":"thenycmaid@gmail.com","phone":"2122029220","active":false,"created_at":"2026-02-09T22:59:29.549861","pin":"737092","working_days":["Mon","Tue","Wed","Thu","Fri","Sat","Sun"],"working_start":"09:00:00","working_end":"17:00:00","photo_url":"https://ioppmvchszymwswtwsze.supabase.co/storage/v1/object/public/cleaner-photo/cleaner-photos/1770678931478-w2ifbn.png","schedule":{"Fri": {"end": "5:00 PM", "start": "9:00 AM"}, "Mon": {"end": "5:00 PM", "start": "9:00 AM"}, "Sat": {"end": "5:00 PM", "start": "9:00 AM"}, "Sun": {"end": "5:00 PM", "start": "9:00 AM"}, "Thu": {"end": "5:00 PM", "start": "9:00 AM"}, "Tue": {"end": "5:00 PM", "start": "9:00 AM"}, "Wed": {"end": "5:00 PM", "start": "9:00 AM"}},"hourly_rate":25,"address":"150 west 47st, 5A","priority":5,"unavailable_dates":[],"sms_consent":true,"notification_preferences":{"broadcast": {"sms": true, "push": true, "email": true}, "quiet_end": "\"07:00\"", "quiet_start": "\"22:00\"", "job_reminder": {"sms": true, "push": true, "email": true}, "daily_summary": {"sms": true, "push": true, "email": true}, "job_cancelled": {"sms": true, "push": true, "email": true}, "job_assignment": {"sms": true, "push": true, "email": true}, "job_rescheduled": {"sms": true, "push": true, "email": true}}}, 
 {"id":"d4fa8855-d8fd-44be-83a7-e398580685d8","name":"Karina","email":"karinalpz34@gmail.com","phone":"3473390813","active":true,"created_at":"2026-02-05T17:19:45.737099","pin":"0813","working_days":["Mon","Tue","Wed","Fri"],"working_start":"09:00:00","working_end":"17:00:00","photo_url":"https://ioppmvchszymwswtwsze.supabase.co/storage/v1/object/public/cleaner-photo/cleaner-photos/1772598925042-ezl7ky.png","schedule":{"Fri": {"end": "5:00 PM", "start": "9:00 AM"}, "Mon": {"end": "5:00 PM", "start": "9:00 AM"}, "Sat": null, "Thu": null, "Tue": {"end": "5:00 PM", "start": "9:00 AM"}, "Wed": {"end": "5:00 PM", "start": "9:00 AM"}},"hourly_rate":31,"address":null,"priority":1,"unavailable_dates":["2026-03-09","2026-03-10","2026-03-15","2026-03-16"],"sms_consent":true,"notification_preferences":{"broadcast": {"sms": true, "push": true, "email": true}, "quiet_end": "\"07:00\"", "quiet_start": "\"22:00\"", "job_reminder": {"sms": true, "push": true, "email": true}, "daily_summary": {"sms": true, "push": true, "email": true}, "job_cancelled": {"sms": true, "push": true, "email": true}, "job_assignment": {"sms": true, "push": true, "email": true}, "job_rescheduled": {"sms": true, "push": true, "email": true}}}, 
 {"id":"c67fde30-f030-4b2e-8036-49cf5c0a66c8","name":"Eunice Pilar Medina Lozano ","email":"medina_lozano@outlook.com","phone":"9147462167","active":true,"created_at":"2026-02-27T17:36:16.076391","pin":"686592","working_days":["Sat","Sun"],"working_start":"09:00:00","working_end":"17:00:00","photo_url":"https://ioppmvchszymwswtwsze.supabase.co/storage/v1/object/public/cleaner-photo/cleaner-photos/1772211644122-0a5w5h.jpeg","schedule":{"Sat": {"end": "5:00 PM", "start": "9:00 AM"}, "Sun": {"end": "5:00 PM", "start": "9:00 AM"}},"hourly_rate":30,"address":"8948 97th St, Woodhaven, NY 11421, 1 floor","priority":99,"unavailable_dates":[],"sms_consent":true,"notification_preferences":{"broadcast": {"sms": true, "push": true, "email": true}, "quiet_end": "\"07:00\"", "quiet_start": "\"22:00\"", "job_reminder": {"sms": true, "push": true, "email": true}, "daily_summary": {"sms": true, "push": true, "email": true}, "job_cancelled": {"sms": true, "push": true, "email": true}, "job_assignment": {"sms": true, "push": true, "email": true}, "job_rescheduled": {"sms": true, "push": true, "email": true}}}, 
 {"id":"58e77d95-e50e-41e3-b6f7-e7c45f92ddb6","name":"Maria","email":"maria.mt.thompson@gmail.com","phone":"3477793716","active":false,"created_at":"2026-02-05T17:21:31.602382","pin":"3716","working_days":["Sat","Mon","Sun","Fri"],"working_start":"09:00:00","working_end":"17:00:00","photo_url":"https://ioppmvchszymwswtwsze.supabase.co/storage/v1/object/public/cleaner-photo/cleaner-photos/test-1770677707683-4.png","schedule":{"Fri": {"end": "7:00 PM", "start": "2:30 PM"}, "Mon": {"end": "5:00 PM", "start": "1:00 PM"}, "Sat": {"end": "5:00 PM", "start": "9:00 AM"}, "Sun": {"end": "12:00 PM", "start": "8:00 AM"}},"hourly_rate":32.5,"address":null,"priority":3,"unavailable_dates":[],"sms_consent":true,"notification_preferences":{"broadcast": {"sms": true, "push": true, "email": true}, "quiet_end": "\"07:00\"", "quiet_start": "\"22:00\"", "job_reminder": {"sms": true, "push": true, "email": true}, "daily_summary": {"sms": true, "push": true, "email": true}, "job_cancelled": {"sms": true, "push": true, "email": true}, "job_assignment": {"sms": true, "push": true, "email": true}, "job_rescheduled": {"sms": true, "push": true, "email": true}}}, 
 {"id":"69420294-6428-426d-8884-0920b13edc6c","name":"Gloria","email":"gloriafermin1974@gmail.com","phone":"3478451952","active":true,"created_at":"2026-02-05T17:22:26.295408","pin":"1952","working_days":["Mon","Thu","Tue","Wed","Fri","Sat"],"working_start":"09:00:00","working_end":"17:00:00","photo_url":"https://ioppmvchszymwswtwsze.supabase.co/storage/v1/object/public/cleaner-photo/cleaner-photos/1772600253683-omp9wh.jpg","schedule":{"Fri": {"end": "5:00 PM", "start": "9:00 AM"}, "Mon": {"end": "5:00 PM", "start": "10:30 AM"}, "Sat": {"end": "5:00 PM", "start": "9:00 AM"}, "Sun": null, "Thu": {"end": "5:00 PM", "start": "9:00 AM"}, "Tue": {"end": "5:00 PM", "start": "9:00 AM"}, "Wed": {"end": "5:00 PM", "start": "9:00 AM"}},"hourly_rate":30,"address":null,"priority":2,"unavailable_dates":[],"sms_consent":true,"notification_preferences":{"broadcast": {"sms": true, "push": true, "email": true}, "quiet_end": "\"07:00\"", "quiet_start": "\"22:00\"", "job_reminder": {"sms": true, "push": true, "email": true}, "daily_summary": {"sms": true, "push": true, "email": true}, "job_cancelled": {"sms": true, "push": true, "email": true}, "job_assignment": {"sms": true, "push": true, "email": true}, "job_rescheduled": {"sms": true, "push": true, "email": true}}}, 
 {"id":"f43d8759-d4c7-4ee2-ba87-bd4fb87430f2","name":"Maria Hernandez","email":"emmaymaria150916@gmail.com","phone":"9295540298","active":true,"created_at":"2026-03-07T21:23:39.223925","pin":"872572","working_days":["Sat","Sun"],"working_start":"09:00:00","working_end":"17:00:00","photo_url":"https://ioppmvchszymwswtwsze.supabase.co/storage/v1/object/public/cleaner-photo/cleaner-photos/1772918461488-3jgnzy.jpeg","schedule":{"Sat": {"end": "5:00 PM", "start": "9:00 AM"}, "Sun": {"end": "5:00 PM", "start": "9:00 AM"}},"hourly_rate":25,"address":"17 Fulton St","priority":99,"unavailable_dates":[],"sms_consent":true,"notification_preferences":{"broadcast": {"sms": true, "push": true, "email": true}, "quiet_end": "\"07:00\"", "quiet_start": "\"22:00\"", "job_reminder": {"sms": true, "push": true, "email": true}, "daily_summary": {"sms": true, "push": true, "email": true}, "job_cancelled": {"sms": true, "push": true, "email": true}, "job_assignment": {"sms": true, "push": true, "email": true}, "job_rescheduled": {"sms": true, "push": true, "email": true}}}]